saphiera/__init__.py
saphiera/exceptions.py
saphiera/schema/__init__.py
saphiera/schema/field.py
saphiera/schema/validators.py
saphiera/types.py
saphiera-1.0.0.dist-info/LICENSE
saphiera-1.0.0.dist-info/METADATA
saphiera-1.0.0.dist-info/WHEEL
saphiera-1.0.0.dist-info/RECORD
